crl_datacube/__init__.py
crl_datacube/conf.py
crl_datacube/datacube2.py
crl_datacube/storage.py
crl_datacube/utils.py
crl_datacube/test/__init__.py
crl_datacube/test/test_config.py
crl_datacube/test/test_datacube.py
crl_datacube/test/test_storage.py
crl_datacube-0.1.140.dist-info/METADATA
crl_datacube-0.1.140.dist-info/WHEEL
crl_datacube-0.1.140.dist-info/top_level.txt
crl_datacube-0.1.140.dist-info/RECORD
